rvmendillo_image_to_ascii/__init__.py
rvmendillo_image_to_ascii-1.6.4.dist-info/LICENSE
rvmendillo_image_to_ascii-1.6.4.dist-info/METADATA
rvmendillo_image_to_ascii-1.6.4.dist-info/WHEEL
rvmendillo_image_to_ascii-1.6.4.dist-info/top_level.txt
rvmendillo_image_to_ascii-1.6.4.dist-info/RECORD
