Metadata-Version: 2.1
Name: rvmendillo-image-to-ascii
Version: 1.6.4
Summary: Generates and saves ASCII texts and colored images from pixels of an image file or URL
Home-page: https://github.com/rvmendillo/image_to_ascii
Author: Rey Victor Mendillo
Author-email: admin@rvmendillo.com
Project-URL: Bug Tracker, https://github.com/rvmendillo/image_to_ascii/issues
Classifier: Programming Language :: Python :: 3
Classifier: License :: OSI Approved :: MIT License
Classifier: Operating System :: OS Independent
Classifier: Topic :: Scientific/Engineering :: Image Processing
Classifier: Topic :: Text Processing
Requires-Python: >=3.6
License-File: LICENSE
Requires-Dist: Pillow
Requires-Dist: requests
